{
  "version": 1,
  "name": "ZDC - ALL",
  "id": "f376cc69-ed41-4736-8dde-7ff2b1a08c72",
  "updateUrl": "https://vzdc.org/vatis/enroute/ZDC-ALL.json",
  "updateSerial": 2025010701,
  "stations": [
    {
      "id": "6fb11d42-f94f-41f2-b97f-2a8c2ea39795",
      "identifier": "KDCA",
      "name": "Washington National",
      "atisType": "Combined",
      "codeRange": {
        "low": "A",
        "high": "Z"
      },
      "atisFormat": {
        "observationTime": {
          "template": {
            "text": "{time}Z",
            "voice": "{time} ZULU {special}"
          }
        },
        "surfaceWind": {
          "speakLeadingZero": false,
          "magneticVariation": {
            "enabled": false,
            "magneticDegrees": 0
          },
          "standard": {
            "template": {
              "text": "{wind_dir}{wind_spd}KT",
              "voice": "WIND {wind_dir} AT {wind_spd}"
            }
          },
          "standardGust": {
            "template": {
              "text": "{wind_dir}{wind_spd}G{wind_gust}KT",
              "voice": "WIND {wind_dir} AT {wind_spd} GUSTS {wind_gust}"
            }
          },
          "variable": {
            "template": {
              "text": "VRB{wind_spd}KT",
              "voice": "WIND VARIABLE AT {wind_spd}"
            }
          },
          "variableGust": {
            "template": {
              "text": "VRB{wind_spd}G{wind_gust}KT",
              "voice": "WIND VARIABLE AT {wind_spd} GUSTS {wind_gust}"
            }
          },
          "variableDirection": {
            "template": {
              "text": "{wind_vmin}V{wind_vmax}",
              "voice": "WIND VARIABLE BETWEEN {wind_vmin} AND {wind_vmax}"
            }
          },
          "calm": {
            "calmWindSpeed": 2,
            "template": {
              "text": "{wind}",
              "voice": "WIND CALM"
            }
          }
        },
        "visibility": {
          "north": "to the north",
          "northEast": "to the north-east",
          "east": "to the east",
          "southEast": "to the south-east",
          "south": "to the south",
          "southWest": "to the south-west",
          "west": "to the west",
          "northWest": "to the north-west",
          "unlimitedVisibilityVoice": "visibility 10 kilometers or more",
          "unlimitedVisibilityText": "VIS 10KM",
          "includeVisibilitySuffix": true,
          "metersCutoff": 5000,
          "template": {
            "text": "{visibility}",
            "voice": "VISIBILITY {visibility}"
          }
        },
        "presentWeather": {
          "lightIntensity": "light",
          "moderateIntensity": "",
          "heavyIntensity": "heavy",
          "vicinity": "in vicinity",
          "presentWeatherTypes": {
            "DZ": {
              "text": "DZ",
              "spoken": "drizzle"
            },
            "RA": {
              "text": "RA",
              "spoken": "rain"
            },
            "SN": {
              "text": "SN",
              "spoken": "snow"
            },
            "SG": {
              "text": "SG",
              "spoken": "snow grains"
            },
            "IC": {
              "text": "IC",
              "spoken": "ice crystals"
            },
            "PL": {
              "text": "PL",
              "spoken": "ice pellets"
            },
            "GR": {
              "text": "GR",
              "spoken": "hail"
            },
            "GS": {
              "text": "GS",
              "spoken": "small hail"
            },
            "UP": {
              "text": "UP",
              "spoken": "unknown precipitation"
            },
            "BR": {
              "text": "BR",
              "spoken": "mist"
            },
            "FG": {
              "text": "FG",
              "spoken": "fog"
            },
            "FU": {
              "text": "FU",
              "spoken": "smoke"
            },
            "VA": {
              "text": "VA",
              "spoken": "volcanic ash"
            },
            "DU": {
              "text": "DU",
              "spoken": "widespread dust"
            },
            "SA": {
              "text": "SA",
              "spoken": "sand"
            },
            "HZ": {
              "text": "HZ",
              "spoken": "haze"
            },
            "PY": {
              "text": "PY",
              "spoken": "spray"
            },
            "PO": {
              "text": "PO",
              "spoken": "well developed dust, sand whirls"
            },
            "SQ": {
              "text": "SQ",
              "spoken": "squalls"
            },
            "FC": {
              "text": "FC",
              "spoken": "funnel cloud tornado waterspout"
            },
            "SS": {
              "text": "SS",
              "spoken": "sandstorm"
            },
            "DS": {
              "text": "DS",
              "spoken": "dust storm"
            },
            "PR": {
              "text": "PR",
              "spoken": "partial"
            },
            "BC": {
              "text": "BC",
              "spoken": "patches"
            },
            "MI": {
              "text": "MI",
              "spoken": "shallow"
            },
            "DR": {
              "text": "DR",
              "spoken": "low drifting"
            },
            "BL": {
              "text": "BL",
              "spoken": "blowing"
            },
            "SH": {
              "text": "SH",
              "spoken": "showers"
            },
            "TS": {
              "text": "TS",
              "spoken": "thunderstorm"
            },
            "FZ": {
              "text": "FZ",
              "spoken": "freezing"
            }
          },
          "template": {
            "text": "{weather}",
            "voice": "{weather}"
          }
        },
        "recentWeather": {
          "template": {
            "text": "RECENT WEATHER {weather}",
            "voice": "RECENT WEATHER {weather}"
          }
        },
        "clouds": {
          "identifyCeilingLayer": true,
          "convertToMetric": false,
          "isAltitudeInHundreds": false,
          "undeterminedLayerAltitude": {
            "text": "undetermined",
            "voice": "undetermined"
          },
          "types": {
            "FEW": {
              "text": "FEW{altitude}",
              "voice": "few clouds at {altitude}"
            },
            "SCT": {
              "text": "SCT{altitude}{convective}",
              "voice": "{altitude} scattered {convective}"
            },
            "BKN": {
              "text": "BKN{altitude}{convective}",
              "voice": "{altitude} broken {convective}"
            },
            "OVC": {
              "text": "OVC{altitude}{convective}",
              "voice": "{altitude} overcast {convective}"
            },
            "VV": {
              "text": "VV{altitude}",
              "voice": "indefinite ceiling {altitude}"
            },
            "NSC": {
              "text": "NSC",
              "voice": "no significant clouds"
            },
            "NCD": {
              "text": "NCD",
              "voice": "no clouds detected"
            },
            "CLR": {
              "text": "CLR",
              "voice": "sky clear below one-two thousand"
            },
            "SKC": {
              "text": "SKC",
              "voice": "sky clear"
            }
          },
          "convectiveTypes": {
            "CB": "cumulonimbus",
            "TCU": "towering cumulus"
          },
          "template": {
            "text": "{clouds}",
            "voice": "{clouds}"
          }
        },
        "temperature": {
          "usePlusPrefix": false,
          "speakLeadingZero": false,
          "template": {
            "text": "{temp}",
            "voice": "TEMPERATURE {temp}"
          }
        },
        "dewpoint": {
          "usePlusPrefix": false,
          "speakLeadingZero": false,
          "template": {
            "text": "{dewpoint}",
            "voice": "DEWPOINT {dewpoint}"
          }
        },
        "altimeter": {
          "pronounceDecimal": false,
          "template": {
            "text": "A{altimeter} ({altimeter|text})",
            "voice": "ALTIMETER {altimeter}"
          }
        },
        "transitionLevel": {
          "values": [],
          "template": {
            "text": "TRANSITION LEVEL {trl}",
            "voice": "TRANSITION LEVEL {trl}"
          }
        },
        "closingStatement": {
          "autoIncludeClosingStatement": true,
          "template": {
            "text": "...ADVS YOU HAVE INFO {letter}.",
            "voice": "ADVISE ON INITIAL CONTACT, YOU HAVE INFORMATION {letter|word}"
          }
        }
      },
      "notamsBeforeFreeText": false,
      "airportConditionsBeforeFreeText": false,
      "frequency": 123650000,
      "idsEndpoint": "https://ids-websocket.vzdc.org/api/vatis/flow",
      "useNotamPrefix": false,
      "useDecimalTerminology": false,
      "atisVoice": {
        "useTextToSpeech": true,
        "voice": "US Male"
      },
      "presets": [
        {
          "id": "413d0e4b-8e36-4b08-9990-08ecb47bd4bc",
          "ordinal": 0,
          "name": "North VMC",
          "airportConditions": "",
          "notams": "",
          "template": "[FACILITY] ATIS INFO [ATIS_CODE] [TIME]. [WX]. ARRIVALS EXPECT @CVPF_MTV. LNDG AND DEPG RWYS 1, ^33. MULTIPLE APPROACHES IN EFFECT [ARPT_COND] [NOTAMS] @READBACK ",
          "externalGenerator": {
            "enabled": false
          }
        },
        {
          "id": "4397b84a-08e3-41eb-9cd0-31ff76ae6f83",
          "ordinal": 1,
          "name": "North IMC",
          "airportConditions": "",
          "notams": "",
          "template": "[FACILITY] ATIS INFO [ATIS_CODE] [TIME]. [WX]. ARRIVALS EXPECT ILS RWY 1. LNDG AND DEPG RWYS 1, ^33. MULTIPLE APPROACHES IN EFFECT [ARPT_COND] [NOTAMS] @READBACK",
          "externalGenerator": {
            "enabled": false
          }
        },
        {
          "id": "be374996-f173-43f1-9c07-6ff95c993615",
          "ordinal": 2,
          "name": "South IMC",
          "airportConditions": "",
          "notams": "",
          "template": "[FACILITY] ATIS INFO [ATIS_CODE] [TIME]. [WX]. RNAV Z APCH RWY 19. LNDG AND DEPG RWYS 19, ^15. MULTIPLE APPROACHES IN EFFECT [ARPT_COND] [NOTAMS] @READBACK",
          "externalGenerator": {
            "enabled": false
          }
        },
        {
          "id": "df39a714-87da-4c87-ab6d-8b2bda54a31e",
          "ordinal": 3,
          "name": "South VMC",
          "airportConditions": "",
          "notams": "",
          "template": "[FACILITY] ATIS INFO [ATIS_CODE] [TIME]. [WX]. ARRIVALS EXPECT @CVFP_RIV_VIS. LNDG AND DEPG RWYS 19, ^15. MULTIPLE APPROACHES IN EFFECT [ARPT_COND] [NOTAMS] @READBACK",
          "externalGenerator": {
            "enabled": false
          }
        }
      ],
      "contractions": [
        {
          "variableName": "ADVISE_ON_INITIAL_CONTACT",
          "text": "TEST",
          "voice": "TEST"
        },
        {
          "variableName": "READBACK",
          "text": "READBACK ALL RUNWAY ASSIGNMENTS AND HOLD SHORT INSTRUCTIONS ",
          "voice": "READBACK ALL RUNWAY ASSIGNMENTS AND HOLD SHORT INSTRUCTIONS.  "
        },
        {
          "variableName": "NO_PROHIBITED",
          "text": "DO NOT ENTER PROHIBITED AIRSPACE N OF ARPT. ",
          "voice": "DO NOT ENTER PROHIBITED AIRSPACE NORTH OF THE AIRPORT. "
        },
        {
          "variableName": "CVPF_MTV",
          "text": "CVFP MTV 1",
          "voice": "CHARTED VISUAL FLIGHT PROCEDURE MOUNT VERNON VISUAL RUNWAY ONE"
        },
        {
          "variableName": "CVFP_RIV_VIS",
          "text": "CVFP RIV VIS 19",
          "voice": "CHARTED VISUAL FLIGHT PROCEDURE RIVER VISUAL RWY 19"
        }
      ],
      "airportConditionDefinitions": [],
      "notamDefinitions": []
    },
    {
      "id": "ac130f4d-aaba-438a-81e4-b1bca253e176",
      "identifier": "KRDU",
      "name": "Raleigh-Durham",
      "atisType": "Combined",
      "codeRange": {
        "low": "A",
        "high": "Z"
      },
      "atisFormat": {
        "observationTime": {
          "template": {
            "text": "{time}Z",
            "voice": "{time} ZULU {special}"
          }
        },
        "surfaceWind": {
          "speakLeadingZero": false,
          "magneticVariation": {
            "enabled": false,
            "magneticDegrees": 0
          },
          "standard": {
            "template": {
              "text": "{wind_dir}{wind_spd}KT",
              "voice": "WIND {wind_dir} AT {wind_spd}"
            }
          },
          "standardGust": {
            "template": {
              "text": "{wind_dir}{wind_spd}G{wind_gust}KT",
              "voice": "WIND {wind_dir} AT {wind_spd} GUSTS {wind_gust}"
            }
          },
          "variable": {
            "template": {
              "text": "VRB{wind_spd}KT",
              "voice": "WIND VARIABLE AT {wind_spd}"
            }
          },
          "variableGust": {
            "template": {
              "text": "VRB{wind_spd}G{wind_gust}KT",
              "voice": "WIND VARIABLE AT {wind_spd} GUSTS {wind_gust}"
            }
          },
          "variableDirection": {
            "template": {
              "text": "{wind_vmin}V{wind_vmax}",
              "voice": "WIND VARIABLE BETWEEN {wind_vmin} AND {wind_vmax}"
            }
          },
          "calm": {
            "calmWindSpeed": 2,
            "template": {
              "text": "{wind}",
              "voice": "WIND CALM"
            }
          }
        },
        "visibility": {
          "north": "to the north",
          "northEast": "to the north-east",
          "east": "to the east",
          "southEast": "to the south-east",
          "south": "to the south",
          "southWest": "to the south-west",
          "west": "to the west",
          "northWest": "to the north-west",
          "unlimitedVisibilityVoice": "visibility 10 kilometers or more",
          "unlimitedVisibilityText": "VIS 10KM",
          "includeVisibilitySuffix": true,
          "metersCutoff": 5000,
          "template": {
            "text": "{visibility}",
            "voice": "VISIBILITY {visibility}"
          }
        },
        "presentWeather": {
          "lightIntensity": "light",
          "moderateIntensity": "",
          "heavyIntensity": "heavy",
          "vicinity": "in vicinity",
          "presentWeatherTypes": {
            "DZ": {
              "text": "DZ",
              "spoken": "drizzle"
            },
            "RA": {
              "text": "RA",
              "spoken": "rain"
            },
            "SN": {
              "text": "SN",
              "spoken": "snow"
            },
            "SG": {
              "text": "SG",
              "spoken": "snow grains"
            },
            "IC": {
              "text": "IC",
              "spoken": "ice crystals"
            },
            "PL": {
              "text": "PL",
              "spoken": "ice pellets"
            },
            "GR": {
              "text": "GR",
              "spoken": "hail"
            },
            "GS": {
              "text": "GS",
              "spoken": "small hail"
            },
            "UP": {
              "text": "UP",
              "spoken": "unknown precipitation"
            },
            "BR": {
              "text": "BR",
              "spoken": "mist"
            },
            "FG": {
              "text": "FG",
              "spoken": "fog"
            },
            "FU": {
              "text": "FU",
              "spoken": "smoke"
            },
            "VA": {
              "text": "VA",
              "spoken": "volcanic ash"
            },
            "DU": {
              "text": "DU",
              "spoken": "widespread dust"
            },
            "SA": {
              "text": "SA",
              "spoken": "sand"
            },
            "HZ": {
              "text": "HZ",
              "spoken": "haze"
            },
            "PY": {
              "text": "PY",
              "spoken": "spray"
            },
            "PO": {
              "text": "PO",
              "spoken": "well developed dust, sand whirls"
            },
            "SQ": {
              "text": "SQ",
              "spoken": "squalls"
            },
            "FC": {
              "text": "FC",
              "spoken": "funnel cloud tornado waterspout"
            },
            "SS": {
              "text": "SS",
              "spoken": "sandstorm"
            },
            "DS": {
              "text": "DS",
              "spoken": "dust storm"
            },
            "PR": {
              "text": "PR",
              "spoken": "partial"
            },
            "BC": {
              "text": "BC",
              "spoken": "patches"
            },
            "MI": {
              "text": "MI",
              "spoken": "shallow"
            },
            "DR": {
              "text": "DR",
              "spoken": "low drifting"
            },
            "BL": {
              "text": "BL",
              "spoken": "blowing"
            },
            "SH": {
              "text": "SH",
              "spoken": "showers"
            },
            "TS": {
              "text": "TS",
              "spoken": "thunderstorm"
            },
            "FZ": {
              "text": "FZ",
              "spoken": "freezing"
            }
          },
          "template": {
            "text": "{weather}",
            "voice": "{weather}"
          }
        },
        "recentWeather": {
          "template": {
            "text": "RECENT WEATHER {weather}",
            "voice": "RECENT WEATHER {weather}"
          }
        },
        "clouds": {
          "identifyCeilingLayer": true,
          "convertToMetric": false,
          "isAltitudeInHundreds": false,
          "undeterminedLayerAltitude": {
            "text": "undetermined",
            "voice": "undetermined"
          },
          "types": {
            "FEW": {
              "text": "FEW{altitude}",
              "voice": "few clouds at {altitude}"
            },
            "SCT": {
              "text": "SCT{altitude}{convective}",
              "voice": "{altitude} scattered {convective}"
            },
            "BKN": {
              "text": "BKN{altitude}{convective}",
              "voice": "{altitude} broken {convective}"
            },
            "OVC": {
              "text": "OVC{altitude}{convective}",
              "voice": "{altitude} overcast {convective}"
            },
            "VV": {
              "text": "VV{altitude}",
              "voice": "indefinite ceiling {altitude}"
            },
            "NSC": {
              "text": "NSC",
              "voice": "no significant clouds"
            },
            "NCD": {
              "text": "NCD",
              "voice": "no clouds detected"
            },
            "CLR": {
              "text": "CLR",
              "voice": "sky clear below one-two thousand"
            },
            "SKC": {
              "text": "SKC",
              "voice": "sky clear"
            }
          },
          "convectiveTypes": {
            "CB": "cumulonimbus",
            "TCU": "towering cumulus"
          },
          "template": {
            "text": "{clouds}",
            "voice": "{clouds}"
          }
        },
        "temperature": {
          "usePlusPrefix": false,
          "speakLeadingZero": false,
          "template": {
            "text": "{temp}",
            "voice": "TEMPERATURE {temp}"
          }
        },
        "dewpoint": {
          "usePlusPrefix": false,
          "speakLeadingZero": false,
          "template": {
            "text": "{dewpoint}",
            "voice": "DEWPOINT {dewpoint}"
          }
        },
        "altimeter": {
          "pronounceDecimal": false,
          "template": {
            "text": "A{altimeter} ({altimeter|text})",
            "voice": "ALTIMETER {altimeter}"
          }
        },
        "transitionLevel": {
          "values": [],
          "template": {
            "text": "TRANSITION LEVEL {trl}",
            "voice": "TRANSITION LEVEL {trl}"
          }
        },
        "closingStatement": {
          "autoIncludeClosingStatement": true,
          "template": {
            "text": "...ADVS YOU HAVE INFO {letter}.",
            "voice": "ADVISE ON INITIAL CONTACT, YOU HAVE INFORMATION {letter|word}"
          }
        }
      },
      "notamsBeforeFreeText": false,
      "airportConditionsBeforeFreeText": false,
      "frequency": 123800000,
      "idsEndpoint": "https://ids-websocket.vzdc.org/api/vatis/flow",
      "useNotamPrefix": false,
      "useDecimalTerminology": false,
      "atisVoice": {
        "useTextToSpeech": true,
        "voice": "US Male"
      },
      "presets": [
        {
          "id": "ffa29364-e383-40f7-83fa-b256c4361125",
          "ordinal": 0,
          "name": "West",
          "template": "[FACILITY] ATIS INFO [ATIS_CODE] [TIME]. [WX]. SIMUL DEPENDENT AND CNVGING APCHS IN USE. EXPECT ILS/VA APCH RWYS 23L, ^23R. MULTIPLE APPROACHES IN EFFECT. LNDG AND DEPG RWYS 23L, ^23R. RWY 14/32 AVAIL UPON REQUEST. [ARPT_COND] [NOTAMS]. ADG IV OR LARGER ACFT AT NORTH CARGO CTC GC PRIOR TO PUSHBACK. @READBACK",
          "externalGenerator": {
            "enabled": false
          }
        },
        {
          "id": "b0f72347-402b-4cc4-9274-95e8a556d56a",
          "ordinal": 1,
          "name": "East",
          "template": "[FACILITY] ATIS INFO [ATIS_CODE] [TIME]. [WX]. SIMUL DEPENDENT AND CNVGING APCHS IN USE. EXPECT ILS/VA APCH RWYS 5L, ^5R. MULTIPLE APPROACHES IN EFFECT. LNDG AND DEPG RWYS 5L, ^5R. RWY 14/32 AVAIL UPON REQUEST. [ARPT_COND] [NOTAMS]. ADG IV OR LARGER ACFT AT NORTH CARGO CTC GC PRIOR TO PUSHBACK. @READBACK",
          "externalGenerator": {
            "enabled": false
          }
        }
      ],
      "contractions": [
        {
          "variableName": "READBACK",
          "text": "READBACK ALL RUNWAY ASSIGNMENTS AND HOLD SHORT INSTRUCTIONS",
          "voice": "READBACK ALL RUNWAY ASSIGNMENTS AND HOLD SHORT INSTRUCTIONS"
        }
      ],
      "airportConditionDefinitions": [],
      "notamDefinitions": []
    },
    {
      "id": "29542f81-c1d9-4de4-9dfd-7bd9e1074c68",
      "identifier": "KROA",
      "name": "Roanoke",
      "atisType": "Combined",
      "codeRange": {
        "low": "A",
        "high": "Z"
      },
      "atisFormat": {
        "observationTime": {
          "template": {
            "text": "{time}Z",
            "voice": "{time} ZULU {special}"
          }
        },
        "surfaceWind": {
          "speakLeadingZero": false,
          "magneticVariation": {
            "enabled": false,
            "magneticDegrees": 0
          },
          "standard": {
            "template": {
              "text": "{wind_dir}{wind_spd}KT",
              "voice": "WIND {wind_dir} AT {wind_spd}"
            }
          },
          "standardGust": {
            "template": {
              "text": "{wind_dir}{wind_spd}G{wind_gust}KT",
              "voice": "WIND {wind_dir} AT {wind_spd} GUSTS {wind_gust}"
            }
          },
          "variable": {
            "template": {
              "text": "VRB{wind_spd}KT",
              "voice": "WIND VARIABLE AT {wind_spd}"
            }
          },
          "variableGust": {
            "template": {
              "text": "VRB{wind_spd}G{wind_gust}KT",
              "voice": "WIND VARIABLE AT {wind_spd} GUSTS {wind_gust}"
            }
          },
          "variableDirection": {
            "template": {
              "text": "{wind_vmin}V{wind_vmax}",
              "voice": "WIND VARIABLE BETWEEN {wind_vmin} AND {wind_vmax}"
            }
          },
          "calm": {
            "calmWindSpeed": 2,
            "template": {
              "text": "{wind}",
              "voice": "WIND CALM"
            }
          }
        },
        "visibility": {
          "north": "to the north",
          "northEast": "to the north-east",
          "east": "to the east",
          "southEast": "to the south-east",
          "south": "to the south",
          "southWest": "to the south-west",
          "west": "to the west",
          "northWest": "to the north-west",
          "unlimitedVisibilityVoice": "visibility 10 kilometers or more",
          "unlimitedVisibilityText": "VIS 10KM",
          "includeVisibilitySuffix": true,
          "metersCutoff": 5000,
          "template": {
            "text": "{visibility}",
            "voice": "VISIBILITY {visibility}"
          }
        },
        "presentWeather": {
          "lightIntensity": "light",
          "moderateIntensity": "",
          "heavyIntensity": "heavy",
          "vicinity": "in vicinity",
          "presentWeatherTypes": {
            "DZ": {
              "text": "DZ",
              "spoken": "drizzle"
            },
            "RA": {
              "text": "RA",
              "spoken": "rain"
            },
            "SN": {
              "text": "SN",
              "spoken": "snow"
            },
            "SG": {
              "text": "SG",
              "spoken": "snow grains"
            },
            "IC": {
              "text": "IC",
              "spoken": "ice crystals"
            },
            "PL": {
              "text": "PL",
              "spoken": "ice pellets"
            },
            "GR": {
              "text": "GR",
              "spoken": "hail"
            },
            "GS": {
              "text": "GS",
              "spoken": "small hail"
            },
            "UP": {
              "text": "UP",
              "spoken": "unknown precipitation"
            },
            "BR": {
              "text": "BR",
              "spoken": "mist"
            },
            "FG": {
              "text": "FG",
              "spoken": "fog"
            },
            "FU": {
              "text": "FU",
              "spoken": "smoke"
            },
            "VA": {
              "text": "VA",
              "spoken": "volcanic ash"
            },
            "DU": {
              "text": "DU",
              "spoken": "widespread dust"
            },
            "SA": {
              "text": "SA",
              "spoken": "sand"
            },
            "HZ": {
              "text": "HZ",
              "spoken": "haze"
            },
            "PY": {
              "text": "PY",
              "spoken": "spray"
            },
            "PO": {
              "text": "PO",
              "spoken": "well developed dust, sand whirls"
            },
            "SQ": {
              "text": "SQ",
              "spoken": "squalls"
            },
            "FC": {
              "text": "FC",
              "spoken": "funnel cloud tornado waterspout"
            },
            "SS": {
              "text": "SS",
              "spoken": "sandstorm"
            },
            "DS": {
              "text": "DS",
              "spoken": "dust storm"
            },
            "PR": {
              "text": "PR",
              "spoken": "partial"
            },
            "BC": {
              "text": "BC",
              "spoken": "patches"
            },
            "MI": {
              "text": "MI",
              "spoken": "shallow"
            },
            "DR": {
              "text": "DR",
              "spoken": "low drifting"
            },
            "BL": {
              "text": "BL",
              "spoken": "blowing"
            },
            "SH": {
              "text": "SH",
              "spoken": "showers"
            },
            "TS": {
              "text": "TS",
              "spoken": "thunderstorm"
            },
            "FZ": {
              "text": "FZ",
              "spoken": "freezing"
            }
          },
          "template": {
            "text": "{weather}",
            "voice": "{weather}"
          }
        },
        "recentWeather": {
          "template": {
            "text": "RECENT WEATHER {weather}",
            "voice": "RECENT WEATHER {weather}"
          }
        },
        "clouds": {
          "identifyCeilingLayer": true,
          "convertToMetric": false,
          "isAltitudeInHundreds": false,
          "undeterminedLayerAltitude": {
            "text": "undetermined",
            "voice": "undetermined"
          },
          "types": {
            "FEW": {
              "text": "FEW{altitude}",
              "voice": "few clouds at {altitude}"
            },
            "SCT": {
              "text": "SCT{altitude}{convective}",
              "voice": "{altitude} scattered {convective}"
            },
            "BKN": {
              "text": "BKN{altitude}{convective}",
              "voice": "{altitude} broken {convective}"
            },
            "OVC": {
              "text": "OVC{altitude}{convective}",
              "voice": "{altitude} overcast {convective}"
            },
            "VV": {
              "text": "VV{altitude}",
              "voice": "indefinite ceiling {altitude}"
            },
            "NSC": {
              "text": "NSC",
              "voice": "no significant clouds"
            },
            "NCD": {
              "text": "NCD",
              "voice": "no clouds detected"
            },
            "CLR": {
              "text": "CLR",
              "voice": "sky clear below one-two thousand"
            },
            "SKC": {
              "text": "SKC",
              "voice": "sky clear"
            }
          },
          "convectiveTypes": {
            "CB": "cumulonimbus",
            "TCU": "towering cumulus"
          },
          "template": {
            "text": "{clouds}",
            "voice": "{clouds}"
          }
        },
        "temperature": {
          "usePlusPrefix": false,
          "speakLeadingZero": false,
          "template": {
            "text": "{temp}",
            "voice": "TEMPERATURE {temp}"
          }
        },
        "dewpoint": {
          "usePlusPrefix": false,
          "speakLeadingZero": false,
          "template": {
            "text": "{dewpoint}",
            "voice": "DEWPOINT {dewpoint}"
          }
        },
        "altimeter": {
          "pronounceDecimal": false,
          "template": {
            "text": "A{altimeter} ({altimeter|text})",
            "voice": "ALTIMETER {altimeter}"
          }
        },
        "transitionLevel": {
          "values": [],
          "template": {
            "text": "TRANSITION LEVEL {trl}",
            "voice": "TRANSITION LEVEL {trl}"
          }
        },
        "closingStatement": {
          "autoIncludeClosingStatement": true,
          "template": {
            "text": "...ADVS YOU HAVE INFO {letter}.",
            "voice": "ADVISE ON INITIAL CONTACT, YOU HAVE INFORMATION {letter|word}"
          }
        }
      },
      "notamsBeforeFreeText": false,
      "airportConditionsBeforeFreeText": false,
      "frequency": 132375000,
      "idsEndpoint": "https://ids-websocket.vzdc.org/api/vatis/flow",
      "useNotamPrefix": false,
      "useDecimalTerminology": false,
      "atisVoice": {
        "useTextToSpeech": true,
        "voice": "US Male"
      },
      "presets": [
        {
          "id": "c50094f5-fbcd-4e0e-a86d-58a698122593",
          "ordinal": 0,
          "name": "06",
          "template": "[FACILITY] ATIS INFO [ATIS_CODE] [TIME]. [WX]. EXPECT VA OR RNAV Z APCH RWY 6. MULTIPLE APPROACHES IN EFFECT. LNDG AND DEPG RWY 6. [ARPT_COND] [NOTAMS] @READBACK",
          "externalGenerator": {
            "enabled": false
          }
        },
        {
          "id": "64f77380-ae22-46aa-899a-8fb4ea4a2067",
          "ordinal": 1,
          "name": "24",
          "template": "[FACILITY] ATIS INFO [ATIS_CODE] [TIME]. [WX]. EXPECT VA OR RNAV Z APCH RWY 24. MULTIPLE APPROACHES IN EFFECT. LNDG AND DEPG RWY 24. [ARPT_COND] [NOTAMS] @READBACK",
          "externalGenerator": {
            "enabled": false
          }
        },
        {
          "id": "e88eada6-0b5a-4119-b295-45bf4d723079",
          "ordinal": 2,
          "name": "34",
          "template": "[FACILITY] ATIS INFO [ATIS_CODE] [TIME]. [WX]. EXPECT VA OR RNAV Z APCH RWY 34. MULTIPLE APPROACHES IN EFFECT. LNDG AND DEPG RWY 34. [ARPT_COND] [NOTAMS] @READBACK",
          "externalGenerator": {
            "enabled": false
          }
        },
        {
          "id": "a7c93cf4-ddcd-4f60-802b-a2c9be13ee4b",
          "ordinal": 3,
          "name": "16/06",
          "template": "[FACILITY] ATIS INFO [ATIS_CODE] [TIME]. [WX]. EXPECT VA OR RNAV Z APCH RWY 6. MULTIPLE APPROACHES IN EFFECT. LNDG RWY 6, DEPG RWY 16. [ARPT_COND] [NOTAMS] @READBACK",
          "externalGenerator": {
            "enabled": false
          }
        },
        {
          "id": "8553a95b-5afb-41b2-8adf-93eaf324de51",
          "ordinal": 4,
          "name": "16/24",
          "template": "[FACILITY] ATIS INFO [ATIS_CODE] [TIME]. [WX]. EXPECT VA OR RNAV Z APCH RWY 24. MULTIPLE APPROACHES IN EFFECT. LNDG RWY 24, DEPG RWY 16. [ARPT_COND] [NOTAMS] @READBACK",
          "externalGenerator": {
            "enabled": false
          }
        }
      ],
      "contractions": [
        {
          "variableName": "READBACK",
          "text": "READBACK ALL RUNWAY ASSIGNMENTS AND HOLD SHORT INSTRUCTIONS",
          "voice": "READBACK ALL RUNWAY ASSIGNMENTS AND HOLD SHORT INSTRUCTIONS"
        }
      ],
      "airportConditionDefinitions": [],
      "notamDefinitions": []
    },
    {
      "id": "da446b9a-ba21-4779-8f91-10ddc2f6c42b",
      "identifier": "KHEF",
      "name": "Manassas",
      "atisType": "Combined",
      "codeRange": {
        "low": "A",
        "high": "Z"
      },
      "atisFormat": {
        "observationTime": {
          "template": {
            "text": "{time}Z",
            "voice": "{time} ZULU {special}"
          }
        },
        "surfaceWind": {
          "speakLeadingZero": false,
          "magneticVariation": {
            "enabled": false,
            "magneticDegrees": 0
          },
          "standard": {
            "template": {
              "text": "{wind_dir}{wind_spd}KT",
              "voice": "WIND {wind_dir} AT {wind_spd}"
            }
          },
          "standardGust": {
            "template": {
              "text": "{wind_dir}{wind_spd}G{wind_gust}KT",
              "voice": "WIND {wind_dir} AT {wind_spd} GUSTS {wind_gust}"
            }
          },
          "variable": {
            "template": {
              "text": "VRB{wind_spd}KT",
              "voice": "WIND VARIABLE AT {wind_spd}"
            }
          },
          "variableGust": {
            "template": {
              "text": "VRB{wind_spd}G{wind_gust}KT",
              "voice": "WIND VARIABLE AT {wind_spd} GUSTS {wind_gust}"
            }
          },
          "variableDirection": {
            "template": {
              "text": "{wind_vmin}V{wind_vmax}",
              "voice": "WIND VARIABLE BETWEEN {wind_vmin} AND {wind_vmax}"
            }
          },
          "calm": {
            "calmWindSpeed": 2,
            "template": {
              "text": "{wind}",
              "voice": "WIND CALM"
            }
          }
        },
        "visibility": {
          "north": "to the north",
          "northEast": "to the north-east",
          "east": "to the east",
          "southEast": "to the south-east",
          "south": "to the south",
          "southWest": "to the south-west",
          "west": "to the west",
          "northWest": "to the north-west",
          "unlimitedVisibilityVoice": "visibility 10 kilometers or more",
          "unlimitedVisibilityText": "VIS 10KM",
          "includeVisibilitySuffix": true,
          "metersCutoff": 5000,
          "template": {
            "text": "{visibility}",
            "voice": "VISIBILITY {visibility}"
          }
        },
        "presentWeather": {
          "lightIntensity": "light",
          "moderateIntensity": "",
          "heavyIntensity": "heavy",
          "vicinity": "in vicinity",
          "presentWeatherTypes": {
            "DZ": {
              "text": "DZ",
              "spoken": "drizzle"
            },
            "RA": {
              "text": "RA",
              "spoken": "rain"
            },
            "SN": {
              "text": "SN",
              "spoken": "snow"
            },
            "SG": {
              "text": "SG",
              "spoken": "snow grains"
            },
            "IC": {
              "text": "IC",
              "spoken": "ice crystals"
            },
            "PL": {
              "text": "PL",
              "spoken": "ice pellets"
            },
            "GR": {
              "text": "GR",
              "spoken": "hail"
            },
            "GS": {
              "text": "GS",
              "spoken": "small hail"
            },
            "UP": {
              "text": "UP",
              "spoken": "unknown precipitation"
            },
            "BR": {
              "text": "BR",
              "spoken": "mist"
            },
            "FG": {
              "text": "FG",
              "spoken": "fog"
            },
            "FU": {
              "text": "FU",
              "spoken": "smoke"
            },
            "VA": {
              "text": "VA",
              "spoken": "volcanic ash"
            },
            "DU": {
              "text": "DU",
              "spoken": "widespread dust"
            },
            "SA": {
              "text": "SA",
              "spoken": "sand"
            },
            "HZ": {
              "text": "HZ",
              "spoken": "haze"
            },
            "PY": {
              "text": "PY",
              "spoken": "spray"
            },
            "PO": {
              "text": "PO",
              "spoken": "well developed dust, sand whirls"
            },
            "SQ": {
              "text": "SQ",
              "spoken": "squalls"
            },
            "FC": {
              "text": "FC",
              "spoken": "funnel cloud tornado waterspout"
            },
            "SS": {
              "text": "SS",
              "spoken": "sandstorm"
            },
            "DS": {
              "text": "DS",
              "spoken": "dust storm"
            },
            "PR": {
              "text": "PR",
              "spoken": "partial"
            },
            "BC": {
              "text": "BC",
              "spoken": "patches"
            },
            "MI": {
              "text": "MI",
              "spoken": "shallow"
            },
            "DR": {
              "text": "DR",
              "spoken": "low drifting"
            },
            "BL": {
              "text": "BL",
              "spoken": "blowing"
            },
            "SH": {
              "text": "SH",
              "spoken": "showers"
            },
            "TS": {
              "text": "TS",
              "spoken": "thunderstorm"
            },
            "FZ": {
              "text": "FZ",
              "spoken": "freezing"
            }
          },
          "template": {
            "text": "{weather}",
            "voice": "{weather}"
          }
        },
        "recentWeather": {
          "template": {
            "text": "RECENT WEATHER {weather}",
            "voice": "RECENT WEATHER {weather}"
          }
        },
        "clouds": {
          "identifyCeilingLayer": true,
          "convertToMetric": false,
          "isAltitudeInHundreds": false,
          "undeterminedLayerAltitude": {
            "text": "undetermined",
            "voice": "undetermined"
          },
          "types": {
            "FEW": {
              "text": "FEW{altitude}",
              "voice": "few clouds at {altitude}"
            },
            "SCT": {
              "text": "SCT{altitude}{convective}",
              "voice": "{altitude} scattered {convective}"
            },
            "BKN": {
              "text": "BKN{altitude}{convective}",
              "voice": "{altitude} broken {convective}"
            },
            "OVC": {
              "text": "OVC{altitude}{convective}",
              "voice": "{altitude} overcast {convective}"
            },
            "VV": {
              "text": "VV{altitude}",
              "voice": "indefinite ceiling {altitude}"
            },
            "NSC": {
              "text": "NSC",
              "voice": "no significant clouds"
            },
            "NCD": {
              "text": "NCD",
              "voice": "no clouds detected"
            },
            "CLR": {
              "text": "CLR",
              "voice": "sky clear below one-two thousand"
            },
            "SKC": {
              "text": "SKC",
              "voice": "sky clear"
            }
          },
          "convectiveTypes": {
            "CB": "cumulonimbus",
            "TCU": "towering cumulus"
          },
          "template": {
            "text": "{clouds}",
            "voice": "{clouds}"
          }
        },
        "temperature": {
          "usePlusPrefix": false,
          "speakLeadingZero": false,
          "template": {
            "text": "{temp}",
            "voice": "TEMPERATURE {temp}"
          }
        },
        "dewpoint": {
          "usePlusPrefix": false,
          "speakLeadingZero": false,
          "template": {
            "text": "{dewpoint}",
            "voice": "DEWPOINT {dewpoint}"
          }
        },
        "altimeter": {
          "pronounceDecimal": false,
          "template": {
            "text": "A{altimeter} ({altimeter|text})",
            "voice": "ALTIMETER {altimeter}"
          }
        },
        "transitionLevel": {
          "values": [],
          "template": {
            "text": "TRANSITION LEVEL {trl}",
            "voice": "TRANSITION LEVEL {trl}"
          }
        },
        "closingStatement": {
          "autoIncludeClosingStatement": true,
          "template": {
            "text": "...ADVS YOU HAVE INFO {letter}.",
            "voice": "ADVISE ON INITIAL CONTACT, YOU HAVE INFORMATION {letter|word}"
          }
        }
      },
      "notamsBeforeFreeText": false,
      "airportConditionsBeforeFreeText": false,
      "frequency": 125175000,
      "idsEndpoint": "https://ids-websocket.vzdc.org/api/vatis/flow",
      "useNotamPrefix": false,
      "useDecimalTerminology": false,
      "atisVoice": {
        "useTextToSpeech": true,
        "voice": "US Male"
      },
      "presets": [
        {
          "id": "7f671c14-e98b-4403-86db-ee456744caeb",
          "ordinal": 0,
          "name": "North",
          "template": "[FACILITY] ATIS INFO [ATIS_CODE] [TIME]. [WX]. EXPECT ILS/VA RWY 34R. LNDG AND DEPG RWYS 34R, ^34L. [ARPT_COND] [NOTAMS] TWR CLOSED BETWEEN 2230-0630 LOCAL TIME. C-TAF ON 133.1. @READBACK",
          "externalGenerator": {
            "enabled": false
          }
        },
        {
          "id": "e7ea229d-95bb-4e04-8f62-53d5433a3c5f",
          "ordinal": 1,
          "name": "South",
          "template": "[FACILITY] ATIS INFO [ATIS_CODE] [TIME]. [WX]. EXPECT ILS/VA RWY 16L. LNDG AND DEPG RWYS 16R, ^16L. [ARPT_COND] [NOTAMS] @READBACK",
          "externalGenerator": {
            "enabled": false
          }
        }
      ],
      "contractions": [
        {
          "variableName": "READBACK",
          "text": "READBACK ALL RUNWAY ASSIGNMENTS AND HOLD SHORT INSTRUCTIONS",
          "voice": "READBACK ALL RUNWAY ASSIGNMENTS AND HOLD SHORT INSTRUCTIONS"
        }
      ],
      "airportConditionDefinitions": [],
      "notamDefinitions": []
    },
    {
      "id": "9264bb28-6990-4b08-b11d-504311ef42cf",
      "identifier": "KFAY",
      "name": "Fayetteville",
      "atisType": "Combined",
      "codeRange": {
        "low": "A",
        "high": "Z"
      },
      "atisFormat": {
        "observationTime": {
          "template": {
            "text": "{time}Z",
            "voice": "{time} ZULU {special}"
          }
        },
        "surfaceWind": {
          "speakLeadingZero": false,
          "magneticVariation": {
            "enabled": false,
            "magneticDegrees": 0
          },
          "standard": {
            "template": {
              "text": "{wind_dir}{wind_spd}KT",
              "voice": "WIND {wind_dir} AT {wind_spd}"
            }
          },
          "standardGust": {
            "template": {
              "text": "{wind_dir}{wind_spd}G{wind_gust}KT",
              "voice": "WIND {wind_dir} AT {wind_spd} GUSTS {wind_gust}"
            }
          },
          "variable": {
            "template": {
              "text": "VRB{wind_spd}KT",
              "voice": "WIND VARIABLE AT {wind_spd}"
            }
          },
          "variableGust": {
            "template": {
              "text": "VRB{wind_spd}G{wind_gust}KT",
              "voice": "WIND VARIABLE AT {wind_spd} GUSTS {wind_gust}"
            }
          },
          "variableDirection": {
            "template": {
              "text": "{wind_vmin}V{wind_vmax}",
              "voice": "WIND VARIABLE BETWEEN {wind_vmin} AND {wind_vmax}"
            }
          },
          "calm": {
            "calmWindSpeed": 2,
            "template": {
              "text": "{wind}",
              "voice": "WIND CALM"
            }
          }
        },
        "visibility": {
          "north": "to the north",
          "northEast": "to the north-east",
          "east": "to the east",
          "southEast": "to the south-east",
          "south": "to the south",
          "southWest": "to the south-west",
          "west": "to the west",
          "northWest": "to the north-west",
          "unlimitedVisibilityVoice": "visibility 10 kilometers or more",
          "unlimitedVisibilityText": "VIS 10KM",
          "includeVisibilitySuffix": true,
          "metersCutoff": 5000,
          "template": {
            "text": "{visibility}",
            "voice": "VISIBILITY {visibility}"
          }
        },
        "presentWeather": {
          "lightIntensity": "light",
          "moderateIntensity": "",
          "heavyIntensity": "heavy",
          "vicinity": "in vicinity",
          "presentWeatherTypes": {
            "DZ": {
              "text": "DZ",
              "spoken": "drizzle"
            },
            "RA": {
              "text": "RA",
              "spoken": "rain"
            },
            "SN": {
              "text": "SN",
              "spoken": "snow"
            },
            "SG": {
              "text": "SG",
              "spoken": "snow grains"
            },
            "IC": {
              "text": "IC",
              "spoken": "ice crystals"
            },
            "PL": {
              "text": "PL",
              "spoken": "ice pellets"
            },
            "GR": {
              "text": "GR",
              "spoken": "hail"
            },
            "GS": {
              "text": "GS",
              "spoken": "small hail"
            },
            "UP": {
              "text": "UP",
              "spoken": "unknown precipitation"
            },
            "BR": {
              "text": "BR",
              "spoken": "mist"
            },
            "FG": {
              "text": "FG",
              "spoken": "fog"
            },
            "FU": {
              "text": "FU",
              "spoken": "smoke"
            },
            "VA": {
              "text": "VA",
              "spoken": "volcanic ash"
            },
            "DU": {
              "text": "DU",
              "spoken": "widespread dust"
            },
            "SA": {
              "text": "SA",
              "spoken": "sand"
            },
            "HZ": {
              "text": "HZ",
              "spoken": "haze"
            },
            "PY": {
              "text": "PY",
              "spoken": "spray"
            },
            "PO": {
              "text": "PO",
              "spoken": "well developed dust, sand whirls"
            },
            "SQ": {
              "text": "SQ",
              "spoken": "squalls"
            },
            "FC": {
              "text": "FC",
              "spoken": "funnel cloud tornado waterspout"
            },
            "SS": {
              "text": "SS",
              "spoken": "sandstorm"
            },
            "DS": {
              "text": "DS",
              "spoken": "dust storm"
            },
            "PR": {
              "text": "PR",
              "spoken": "partial"
            },
            "BC": {
              "text": "BC",
              "spoken": "patches"
            },
            "MI": {
              "text": "MI",
              "spoken": "shallow"
            },
            "DR": {
              "text": "DR",
              "spoken": "low drifting"
            },
            "BL": {
              "text": "BL",
              "spoken": "blowing"
            },
            "SH": {
              "text": "SH",
              "spoken": "showers"
            },
            "TS": {
              "text": "TS",
              "spoken": "thunderstorm"
            },
            "FZ": {
              "text": "FZ",
              "spoken": "freezing"
            }
          },
          "template": {
            "text": "{weather}",
            "voice": "{weather}"
          }
        },
        "recentWeather": {
          "template": {
            "text": "RECENT WEATHER {weather}",
            "voice": "RECENT WEATHER {weather}"
          }
        },
        "clouds": {
          "identifyCeilingLayer": true,
          "convertToMetric": false,
          "isAltitudeInHundreds": false,
          "undeterminedLayerAltitude": {
            "text": "undetermined",
            "voice": "undetermined"
          },
          "types": {
            "FEW": {
              "text": "FEW{altitude}",
              "voice": "few clouds at {altitude}"
            },
            "SCT": {
              "text": "SCT{altitude}{convective}",
              "voice": "{altitude} scattered {convective}"
            },
            "BKN": {
              "text": "BKN{altitude}{convective}",
              "voice": "{altitude} broken {convective}"
            },
            "OVC": {
              "text": "OVC{altitude}{convective}",
              "voice": "{altitude} overcast {convective}"
            },
            "VV": {
              "text": "VV{altitude}",
              "voice": "indefinite ceiling {altitude}"
            },
            "NSC": {
              "text": "NSC",
              "voice": "no significant clouds"
            },
            "NCD": {
              "text": "NCD",
              "voice": "no clouds detected"
            },
            "CLR": {
              "text": "CLR",
              "voice": "sky clear below one-two thousand"
            },
            "SKC": {
              "text": "SKC",
              "voice": "sky clear"
            }
          },
          "convectiveTypes": {
            "CB": "cumulonimbus",
            "TCU": "towering cumulus"
          },
          "template": {
            "text": "{clouds}",
            "voice": "{clouds}"
          }
        },
        "temperature": {
          "usePlusPrefix": false,
          "speakLeadingZero": false,
          "template": {
            "text": "{temp}",
            "voice": "TEMPERATURE {temp}"
          }
        },
        "dewpoint": {
          "usePlusPrefix": false,
          "speakLeadingZero": false,
          "template": {
            "text": "{dewpoint}",
            "voice": "DEWPOINT {dewpoint}"
          }
        },
        "altimeter": {
          "pronounceDecimal": false,
          "template": {
            "text": "A{altimeter} ({altimeter|text})",
            "voice": "ALTIMETER {altimeter}"
          }
        },
        "transitionLevel": {
          "values": [],
          "template": {
            "text": "TRANSITION LEVEL {trl}",
            "voice": "TRANSITION LEVEL {trl}"
          }
        },
        "closingStatement": {
          "autoIncludeClosingStatement": true,
          "template": {
            "text": "...ADVS YOU HAVE INFO {letter}.",
            "voice": "ADVISE ON INITIAL CONTACT, YOU HAVE INFORMATION {letter|word}"
          }
        }
      },
      "notamsBeforeFreeText": false,
      "airportConditionsBeforeFreeText": false,
      "frequency": 121250000,
      "idsEndpoint": "https://ids-websocket.vzdc.org/api/vatis/flow",
      "useNotamPrefix": false,
      "useDecimalTerminology": false,
      "atisVoice": {
        "useTextToSpeech": true,
        "voice": "US Male"
      },
      "presets": [
        {
          "id": "0038a955-2fed-4be8-82d6-0926fcc74a5a",
          "ordinal": 0,
          "name": "East w/10",
          "template": "[FACILITY] ATIS INFO [ATIS_CODE] [TIME]. [WX]. EXPECT ILS/VA APCH RWY 4. MULTIPLE APPROACHES IN EFFECT. LNDG AND DEPG RWY 4. RWY 10 AVAIL UPON REQUEST. [ARPT_COND] [NOTAMS] @READBACK",
          "externalGenerator": {
            "enabled": false
          }
        },
        {
          "id": "5763f30c-9353-4e0a-96b9-87fc66898d55",
          "ordinal": 1,
          "name": "West w/28",
          "template": "[FACILITY] ATIS INFO [ATIS_CODE] [TIME]. [WX]. EXPECT ILS/VA APCH RWY 22. MULTIPLE APPROACHES IN EFFECT. LNDG AND DEPG RWY 22. RWY 28 AVAIL UPON REQUEST. [ARPT_COND] [NOTAMS] @READBACK",
          "externalGenerator": {
            "enabled": false
          }
        },
        {
          "id": "5ece2c1a-447d-4581-be05-3cf705b7cc88",
          "ordinal": 2,
          "name": "West",
          "template": "[FACILITY] ATIS INFO [ATIS_CODE] [TIME]. [WX]. EXPECT ILS/VA APCH RWY 22. MULTIPLE APPROACHES IN EFFECT. LNDG AND DEPG RWY 22. [ARPT_COND] [NOTAMS] @READBACK",
          "externalGenerator": {
            "enabled": false
          }
        },
        {
          "id": "3c3cac7c-94d6-448b-b057-e44ebd0485b1",
          "ordinal": 3,
          "name": "East",
          "template": "[FACILITY] ATIS INFO [ATIS_CODE] [TIME]. [WX]. EXPECT ILS/VA APCH RWY 4. MULTIPLE APPROACHES IN EFFECT. LNDG AND DEPG RWY 4. [ARPT_COND] [NOTAMS] @READBACK",
          "externalGenerator": {
            "enabled": false
          }
        }
      ],
      "contractions": [
        {
          "variableName": "READBACK",
          "text": "READBACK ALL RUNWAY ASSIGNMENTS AND HOLD SHORT INSTRUCTIONS",
          "voice": "READBACK ALL RUNWAY ASSIGNMENTS AND HOLD SHORT INSTRUCTIONS"
        }
      ],
      "airportConditionDefinitions": [],
      "notamDefinitions": []
    },
    {
      "id": "7faf503c-a8b9-4b53-a1e1-4d248f163c7d",
      "identifier": "KACY",
      "name": "Atlantic City",
      "atisType": "Combined",
      "codeRange": {
        "low": "A",
        "high": "Z"
      },
      "atisFormat": {
        "observationTime": {
          "template": {
            "text": "{time}Z",
            "voice": "{time} ZULU {special}"
          }
        },
        "surfaceWind": {
          "speakLeadingZero": false,
          "magneticVariation": {
            "enabled": false,
            "magneticDegrees": 0
          },
          "standard": {
            "template": {
              "text": "{wind_dir}{wind_spd}KT",
              "voice": "WIND {wind_dir} AT {wind_spd}"
            }
          },
          "standardGust": {
            "template": {
              "text": "{wind_dir}{wind_spd}G{wind_gust}KT",
              "voice": "WIND {wind_dir} AT {wind_spd} GUSTS {wind_gust}"
            }
          },
          "variable": {
            "template": {
              "text": "VRB{wind_spd}KT",
              "voice": "WIND VARIABLE AT {wind_spd}"
            }
          },
          "variableGust": {
            "template": {
              "text": "VRB{wind_spd}G{wind_gust}KT",
              "voice": "WIND VARIABLE AT {wind_spd} GUSTS {wind_gust}"
            }
          },
          "variableDirection": {
            "template": {
              "text": "{wind_vmin}V{wind_vmax}",
              "voice": "WIND VARIABLE BETWEEN {wind_vmin} AND {wind_vmax}"
            }
          },
          "calm": {
            "calmWindSpeed": 2,
            "template": {
              "text": "{wind}",
              "voice": "WIND CALM"
            }
          }
        },
        "visibility": {
          "north": "to the north",
          "northEast": "to the north-east",
          "east": "to the east",
          "southEast": "to the south-east",
          "south": "to the south",
          "southWest": "to the south-west",
          "west": "to the west",
          "northWest": "to the north-west",
          "unlimitedVisibilityVoice": "visibility 10 kilometers or more",
          "unlimitedVisibilityText": "VIS 10KM",
          "includeVisibilitySuffix": true,
          "metersCutoff": 5000,
          "template": {
            "text": "{visibility}",
            "voice": "VISIBILITY {visibility}"
          }
        },
        "presentWeather": {
          "lightIntensity": "light",
          "moderateIntensity": "",
          "heavyIntensity": "heavy",
          "vicinity": "in vicinity",
          "presentWeatherTypes": {
            "DZ": {
              "text": "DZ",
              "spoken": "drizzle"
            },
            "RA": {
              "text": "RA",
              "spoken": "rain"
            },
            "SN": {
              "text": "SN",
              "spoken": "snow"
            },
            "SG": {
              "text": "SG",
              "spoken": "snow grains"
            },
            "IC": {
              "text": "IC",
              "spoken": "ice crystals"
            },
            "PL": {
              "text": "PL",
              "spoken": "ice pellets"
            },
            "GR": {
              "text": "GR",
              "spoken": "hail"
            },
            "GS": {
              "text": "GS",
              "spoken": "small hail"
            },
            "UP": {
              "text": "UP",
              "spoken": "unknown precipitation"
            },
            "BR": {
              "text": "BR",
              "spoken": "mist"
            },
            "FG": {
              "text": "FG",
              "spoken": "fog"
            },
            "FU": {
              "text": "FU",
              "spoken": "smoke"
            },
            "VA": {
              "text": "VA",
              "spoken": "volcanic ash"
            },
            "DU": {
              "text": "DU",
              "spoken": "widespread dust"
            },
            "SA": {
              "text": "SA",
              "spoken": "sand"
            },
            "HZ": {
              "text": "HZ",
              "spoken": "haze"
            },
            "PY": {
              "text": "PY",
              "spoken": "spray"
            },
            "PO": {
              "text": "PO",
              "spoken": "well developed dust, sand whirls"
            },
            "SQ": {
              "text": "SQ",
              "spoken": "squalls"
            },
            "FC": {
              "text": "FC",
              "spoken": "funnel cloud tornado waterspout"
            },
            "SS": {
              "text": "SS",
              "spoken": "sandstorm"
            },
            "DS": {
              "text": "DS",
              "spoken": "dust storm"
            },
            "PR": {
              "text": "PR",
              "spoken": "partial"
            },
            "BC": {
              "text": "BC",
              "spoken": "patches"
            },
            "MI": {
              "text": "MI",
              "spoken": "shallow"
            },
            "DR": {
              "text": "DR",
              "spoken": "low drifting"
            },
            "BL": {
              "text": "BL",
              "spoken": "blowing"
            },
            "SH": {
              "text": "SH",
              "spoken": "showers"
            },
            "TS": {
              "text": "TS",
              "spoken": "thunderstorm"
            },
            "FZ": {
              "text": "FZ",
              "spoken": "freezing"
            }
          },
          "template": {
            "text": "{weather}",
            "voice": "{weather}"
          }
        },
        "recentWeather": {
          "template": {
            "text": "RECENT WEATHER {weather}",
            "voice": "RECENT WEATHER {weather}"
          }
        },
        "clouds": {
          "identifyCeilingLayer": true,
          "convertToMetric": false,
          "isAltitudeInHundreds": false,
          "undeterminedLayerAltitude": {
            "text": "undetermined",
            "voice": "undetermined"
          },
          "types": {
            "FEW": {
              "text": "FEW{altitude}",
              "voice": "few clouds at {altitude}"
            },
            "SCT": {
              "text": "SCT{altitude}{convective}",
              "voice": "{altitude} scattered {convective}"
            },
            "BKN": {
              "text": "BKN{altitude}{convective}",
              "voice": "{altitude} broken {convective}"
            },
            "OVC": {
              "text": "OVC{altitude}{convective}",
              "voice": "{altitude} overcast {convective}"
            },
            "VV": {
              "text": "VV{altitude}",
              "voice": "indefinite ceiling {altitude}"
            },
            "NSC": {
              "text": "NSC",
              "voice": "no significant clouds"
            },
            "NCD": {
              "text": "NCD",
              "voice": "no clouds detected"
            },
            "CLR": {
              "text": "CLR",
              "voice": "sky clear below one-two thousand"
            },
            "SKC": {
              "text": "SKC",
              "voice": "sky clear"
            }
          },
          "convectiveTypes": {
            "CB": "cumulonimbus",
            "TCU": "towering cumulus"
          },
          "template": {
            "text": "{clouds}",
            "voice": "{clouds}"
          }
        },
        "temperature": {
          "usePlusPrefix": false,
          "speakLeadingZero": false,
          "template": {
            "text": "{temp}",
            "voice": "TEMPERATURE {temp}"
          }
        },
        "dewpoint": {
          "usePlusPrefix": false,
          "speakLeadingZero": false,
          "template": {
            "text": "{dewpoint}",
            "voice": "DEWPOINT {dewpoint}"
          }
        },
        "altimeter": {
          "pronounceDecimal": false,
          "template": {
            "text": "A{altimeter} ({altimeter|text})",
            "voice": "ALTIMETER {altimeter}"
          }
        },
        "transitionLevel": {
          "values": [],
          "template": {
            "text": "TRANSITION LEVEL {trl}",
            "voice": "TRANSITION LEVEL {trl}"
          }
        },
        "closingStatement": {
          "autoIncludeClosingStatement": true,
          "template": {
            "text": "...ADVS YOU HAVE INFO {letter}.",
            "voice": "ADVISE ON INITIAL CONTACT, YOU HAVE INFORMATION {letter|word}"
          }
        }
      },
      "notamsBeforeFreeText": false,
      "airportConditionsBeforeFreeText": false,
      "frequency": 125725000,
      "idsEndpoint": "https://ids-websocket.vzdc.org/api/vatis/flow",
      "useNotamPrefix": false,
      "useDecimalTerminology": false,
      "atisVoice": {
        "useTextToSpeech": true,
        "voice": "US Male"
      },
      "presets": [
        {
          "id": "9b0eb66b-2ff3-4cee-bbb8-0caa994145a1",
          "ordinal": 0,
          "name": "South w/22",
          "template": "[FACILITY] ATIS INFO [ATIS_CODE] [TIME]. [WX]. EXPECT ILS/VA APCH RWY 13. MULTIPLE APPROACHES IN EFFECT. LNDG AND DEPG RWY 13. RWY 22 AVAIL UPON REQUEST. [ARPT_COND] [NOTAMS] @READBACK",
          "externalGenerator": {
            "enabled": false
          }
        },
        {
          "id": "422ac51d-1350-4bdf-88a9-44271306c0cd",
          "ordinal": 1,
          "name": "South w/04",
          "template": "[FACILITY] ATIS INFO [ATIS_CODE] [TIME]. [WX]. EXPECT ILS/VA APCH RWY 13. MULTIPLE APPROACHES IN EFFECT. LNDG AND DEPG RWY 13. RWY 4 AVAIL UPON REQUEST. [ARPT_COND] [NOTAMS] @READBACK",
          "externalGenerator": {
            "enabled": false
          }
        },
        {
          "id": "50bb67cd-c035-4701-94a0-d80cb5be23dd",
          "ordinal": 2,
          "name": "North w/04",
          "template": "[FACILITY] ATIS INFO [ATIS_CODE] [TIME]. [WX]. EXPECT ILS/VA APCH RWY 31. MULTIPLE APPROACHES IN EFFECT. LNDG AND DEPG RWY 31. RWY 4 AVAIL UPON REQUEST. [ARPT_COND] [NOTAMS] @READBACK",
          "externalGenerator": {
            "enabled": false
          }
        },
        {
          "id": "2dbe937b-1fe0-454e-b73d-53c299bb5a57",
          "ordinal": 3,
          "name": "North w/22",
          "template": "[FACILITY] ATIS INFO [ATIS_CODE] [TIME]. [WX]. EXPECT ILS/VA APCH RWY 31. MULTIPLE APPROACHES IN EFFECT. LNDG AND DEPG RWY 31. RWY 22 AVAIL UPON REQUEST. [ARPT_COND] [NOTAMS] @READBACK",
          "externalGenerator": {
            "enabled": false
          }
        }
      ],
      "contractions": [
        {
          "variableName": "READBACK",
          "text": "READBACK ALL RUNWAY ASSIGNMENTS AND HOLD SHORT INSTRUCTIONS",
          "voice": "READBACK ALL RUNWAY ASSIGNMENTS AND HOLD SHORT INSTRUCTIONS"
        }
      ],
      "airportConditionDefinitions": [],
      "notamDefinitions": []
    },
    {
      "id": "3eac7bc1-433c-4e56-a935-b6c10f345158",
      "identifier": "KHGR",
      "name": "Hagerstown ASOS",
      "atisType": "Combined",
      "codeRange": {
        "low": "A",
        "high": "Z"
      },
      "atisFormat": {
        "observationTime": {
          "template": {
            "text": "{time}Z",
            "voice": "{time} ZULU {special}"
          }
        },
        "surfaceWind": {
          "speakLeadingZero": false,
          "magneticVariation": {
            "enabled": false,
            "magneticDegrees": 0
          },
          "standard": {
            "template": {
              "text": "{wind_dir}{wind_spd}KT",
              "voice": "WIND {wind_dir} AT {wind_spd}"
            }
          },
          "standardGust": {
            "template": {
              "text": "{wind_dir}{wind_spd}G{wind_gust}KT",
              "voice": "WIND {wind_dir} AT {wind_spd} GUSTS {wind_gust}"
            }
          },
          "variable": {
            "template": {
              "text": "VRB{wind_spd}KT",
              "voice": "WIND VARIABLE AT {wind_spd}"
            }
          },
          "variableGust": {
            "template": {
              "text": "VRB{wind_spd}G{wind_gust}KT",
              "voice": "WIND VARIABLE AT {wind_spd} GUSTS {wind_gust}"
            }
          },
          "variableDirection": {
            "template": {
              "text": "{wind_vmin}V{wind_vmax}",
              "voice": "WIND VARIABLE BETWEEN {wind_vmin} AND {wind_vmax}"
            }
          },
          "calm": {
            "calmWindSpeed": 2,
            "template": {
              "text": "{wind}",
              "voice": "WIND CALM"
            }
          }
        },
        "visibility": {
          "north": "to the north",
          "northEast": "to the north-east",
          "east": "to the east",
          "southEast": "to the south-east",
          "south": "to the south",
          "southWest": "to the south-west",
          "west": "to the west",
          "northWest": "to the north-west",
          "unlimitedVisibilityVoice": "visibility 10 kilometers or more",
          "unlimitedVisibilityText": "VIS 10KM",
          "includeVisibilitySuffix": true,
          "metersCutoff": 5000,
          "template": {
            "text": "{visibility}",
            "voice": "VISIBILITY {visibility}"
          }
        },
        "presentWeather": {
          "lightIntensity": "light",
          "moderateIntensity": "",
          "heavyIntensity": "heavy",
          "vicinity": "in vicinity",
          "presentWeatherTypes": {
            "DZ": {
              "text": "DZ",
              "spoken": "drizzle"
            },
            "RA": {
              "text": "RA",
              "spoken": "rain"
            },
            "SN": {
              "text": "SN",
              "spoken": "snow"
            },
            "SG": {
              "text": "SG",
              "spoken": "snow grains"
            },
            "IC": {
              "text": "IC",
              "spoken": "ice crystals"
            },
            "PL": {
              "text": "PL",
              "spoken": "ice pellets"
            },
            "GR": {
              "text": "GR",
              "spoken": "hail"
            },
            "GS": {
              "text": "GS",
              "spoken": "small hail"
            },
            "UP": {
              "text": "UP",
              "spoken": "unknown precipitation"
            },
            "BR": {
              "text": "BR",
              "spoken": "mist"
            },
            "FG": {
              "text": "FG",
              "spoken": "fog"
            },
            "FU": {
              "text": "FU",
              "spoken": "smoke"
            },
            "VA": {
              "text": "VA",
              "spoken": "volcanic ash"
            },
            "DU": {
              "text": "DU",
              "spoken": "widespread dust"
            },
            "SA": {
              "text": "SA",
              "spoken": "sand"
            },
            "HZ": {
              "text": "HZ",
              "spoken": "haze"
            },
            "PY": {
              "text": "PY",
              "spoken": "spray"
            },
            "PO": {
              "text": "PO",
              "spoken": "well developed dust, sand whirls"
            },
            "SQ": {
              "text": "SQ",
              "spoken": "squalls"
            },
            "FC": {
              "text": "FC",
              "spoken": "funnel cloud tornado waterspout"
            },
            "SS": {
              "text": "SS",
              "spoken": "sandstorm"
            },
            "DS": {
              "text": "DS",
              "spoken": "dust storm"
            },
            "PR": {
              "text": "PR",
              "spoken": "partial"
            },
            "BC": {
              "text": "BC",
              "spoken": "patches"
            },
            "MI": {
              "text": "MI",
              "spoken": "shallow"
            },
            "DR": {
              "text": "DR",
              "spoken": "low drifting"
            },
            "BL": {
              "text": "BL",
              "spoken": "blowing"
            },
            "SH": {
              "text": "SH",
              "spoken": "showers"
            },
            "TS": {
              "text": "TS",
              "spoken": "thunderstorm"
            },
            "FZ": {
              "text": "FZ",
              "spoken": "freezing"
            }
          },
          "template": {
            "text": "{weather}",
            "voice": "{weather}"
          }
        },
        "recentWeather": {
          "template": {
            "text": "RECENT WEATHER {weather}",
            "voice": "RECENT WEATHER {weather}"
          }
        },
        "clouds": {
          "identifyCeilingLayer": true,
          "convertToMetric": false,
          "isAltitudeInHundreds": false,
          "undeterminedLayerAltitude": {
            "text": "undetermined",
            "voice": "undetermined"
          },
          "types": {
            "FEW": {
              "text": "FEW{altitude}",
              "voice": "few clouds at {altitude}"
            },
            "SCT": {
              "text": "SCT{altitude}{convective}",
              "voice": "{altitude} scattered {convective}"
            },
            "BKN": {
              "text": "BKN{altitude}{convective}",
              "voice": "{altitude} broken {convective}"
            },
            "OVC": {
              "text": "OVC{altitude}{convective}",
              "voice": "{altitude} overcast {convective}"
            },
            "VV": {
              "text": "VV{altitude}",
              "voice": "indefinite ceiling {altitude}"
            },
            "NSC": {
              "text": "NSC",
              "voice": "no significant clouds"
            },
            "NCD": {
              "text": "NCD",
              "voice": "no clouds detected"
            },
            "CLR": {
              "text": "CLR",
              "voice": "sky clear below one-two thousand"
            },
            "SKC": {
              "text": "SKC",
              "voice": "sky clear"
            }
          },
          "convectiveTypes": {
            "CB": "cumulonimbus",
            "TCU": "towering cumulus"
          },
          "template": {
            "text": "{clouds}",
            "voice": "{clouds}"
          }
        },
        "temperature": {
          "usePlusPrefix": false,
          "speakLeadingZero": false,
          "template": {
            "text": "{temp}",
            "voice": "TEMPERATURE {temp}"
          }
        },
        "dewpoint": {
          "usePlusPrefix": false,
          "speakLeadingZero": false,
          "template": {
            "text": "{dewpoint}",
            "voice": "DEWPOINT {dewpoint}"
          }
        },
        "altimeter": {
          "pronounceDecimal": false,
          "template": {
            "text": "A{altimeter} ({altimeter|text})",
            "voice": "ALTIMETER {altimeter}"
          }
        },
        "transitionLevel": {
          "values": [],
          "template": {
            "text": "TRANSITION LEVEL {trl}",
            "voice": "TRANSITION LEVEL {trl}"
          }
        },
        "closingStatement": {
          "autoIncludeClosingStatement": false,
          "template": {
            "text": "...ADVS YOU HAVE INFO {letter}.",
            "voice": "ADVISE ON INITIAL CONTACT, YOU HAVE INFORMATION {letter|word}"
          }
        }
      },
      "notamsBeforeFreeText": false,
      "airportConditionsBeforeFreeText": false,
      "frequency": 126375000,
      "useNotamPrefix": false,
      "useDecimalTerminology": false,
      "atisVoice": {
        "useTextToSpeech": true,
        "voice": "US Male"
      },
      "presets": [
        {
          "id": "f6e7d138-7e97-4bc7-ada2-1c2db651aa35",
          "ordinal": 0,
          "name": "ASOS",
          "template": "[FACILITY] AUTOMATED WEATHER OBSERVATION, [TIME]. [WX].",
          "externalGenerator": {
            "enabled": false
          }
        }
      ],
      "contractions": [],
      "airportConditionDefinitions": [],
      "notamDefinitions": []
    },
    {
      "id": "aca208e6-a5ac-4158-91cf-6125fcdcacfc",
      "identifier": "KLWB",
      "name": "Greenbrier",
      "atisType": "Combined",
      "codeRange": {
        "low": "A",
        "high": "Z"
      },
      "atisFormat": {
        "observationTime": {
          "template": {
            "text": "{time}Z",
            "voice": "{time} ZULU {special}"
          }
        },
        "surfaceWind": {
          "speakLeadingZero": false,
          "magneticVariation": {
            "enabled": false,
            "magneticDegrees": 0
          },
          "standard": {
            "template": {
              "text": "{wind_dir}{wind_spd}KT",
              "voice": "WIND {wind_dir} AT {wind_spd}"
            }
          },
          "standardGust": {
            "template": {
              "text": "{wind_dir}{wind_spd}G{wind_gust}KT",
              "voice": "WIND {wind_dir} AT {wind_spd} GUSTS {wind_gust}"
            }
          },
          "variable": {
            "template": {
              "text": "VRB{wind_spd}KT",
              "voice": "WIND VARIABLE AT {wind_spd}"
            }
          },
          "variableGust": {
            "template": {
              "text": "VRB{wind_spd}G{wind_gust}KT",
              "voice": "WIND VARIABLE AT {wind_spd} GUSTS {wind_gust}"
            }
          },
          "variableDirection": {
            "template": {
              "text": "{wind_vmin}V{wind_vmax}",
              "voice": "WIND VARIABLE BETWEEN {wind_vmin} AND {wind_vmax}"
            }
          },
          "calm": {
            "calmWindSpeed": 2,
            "template": {
              "text": "{wind}",
              "voice": "WIND CALM"
            }
          }
        },
        "visibility": {
          "north": "to the north",
          "northEast": "to the north-east",
          "east": "to the east",
          "southEast": "to the south-east",
          "south": "to the south",
          "southWest": "to the south-west",
          "west": "to the west",
          "northWest": "to the north-west",
          "unlimitedVisibilityVoice": "visibility 10 kilometers or more",
          "unlimitedVisibilityText": "VIS 10KM",
          "includeVisibilitySuffix": true,
          "metersCutoff": 5000,
          "template": {
            "text": "{visibility}",
            "voice": "VISIBILITY {visibility}"
          }
        },
        "presentWeather": {
          "lightIntensity": "light",
          "moderateIntensity": "",
          "heavyIntensity": "heavy",
          "vicinity": "in vicinity",
          "presentWeatherTypes": {
            "DZ": {
              "text": "DZ",
              "spoken": "drizzle"
            },
            "RA": {
              "text": "RA",
              "spoken": "rain"
            },
            "SN": {
              "text": "SN",
              "spoken": "snow"
            },
            "SG": {
              "text": "SG",
              "spoken": "snow grains"
            },
            "IC": {
              "text": "IC",
              "spoken": "ice crystals"
            },
            "PL": {
              "text": "PL",
              "spoken": "ice pellets"
            },
            "GR": {
              "text": "GR",
              "spoken": "hail"
            },
            "GS": {
              "text": "GS",
              "spoken": "small hail"
            },
            "UP": {
              "text": "UP",
              "spoken": "unknown precipitation"
            },
            "BR": {
              "text": "BR",
              "spoken": "mist"
            },
            "FG": {
              "text": "FG",
              "spoken": "fog"
            },
            "FU": {
              "text": "FU",
              "spoken": "smoke"
            },
            "VA": {
              "text": "VA",
              "spoken": "volcanic ash"
            },
            "DU": {
              "text": "DU",
              "spoken": "widespread dust"
            },
            "SA": {
              "text": "SA",
              "spoken": "sand"
            },
            "HZ": {
              "text": "HZ",
              "spoken": "haze"
            },
            "PY": {
              "text": "PY",
              "spoken": "spray"
            },
            "PO": {
              "text": "PO",
              "spoken": "well developed dust, sand whirls"
            },
            "SQ": {
              "text": "SQ",
              "spoken": "squalls"
            },
            "FC": {
              "text": "FC",
              "spoken": "funnel cloud tornado waterspout"
            },
            "SS": {
              "text": "SS",
              "spoken": "sandstorm"
            },
            "DS": {
              "text": "DS",
              "spoken": "dust storm"
            },
            "PR": {
              "text": "PR",
              "spoken": "partial"
            },
            "BC": {
              "text": "BC",
              "spoken": "patches"
            },
            "MI": {
              "text": "MI",
              "spoken": "shallow"
            },
            "DR": {
              "text": "DR",
              "spoken": "low drifting"
            },
            "BL": {
              "text": "BL",
              "spoken": "blowing"
            },
            "SH": {
              "text": "SH",
              "spoken": "showers"
            },
            "TS": {
              "text": "TS",
              "spoken": "thunderstorm"
            },
            "FZ": {
              "text": "FZ",
              "spoken": "freezing"
            }
          },
          "template": {
            "text": "{weather}",
            "voice": "{weather}"
          }
        },
        "recentWeather": {
          "template": {
            "text": "RECENT WEATHER {weather}",
            "voice": "RECENT WEATHER {weather}"
          }
        },
        "clouds": {
          "identifyCeilingLayer": true,
          "convertToMetric": false,
          "isAltitudeInHundreds": false,
          "undeterminedLayerAltitude": {
            "text": "undetermined",
            "voice": "undetermined"
          },
          "types": {
            "FEW": {
              "text": "FEW{altitude}",
              "voice": "few clouds at {altitude}"
            },
            "SCT": {
              "text": "SCT{altitude}{convective}",
              "voice": "{altitude} scattered {convective}"
            },
            "BKN": {
              "text": "BKN{altitude}{convective}",
              "voice": "{altitude} broken {convective}"
            },
            "OVC": {
              "text": "OVC{altitude}{convective}",
              "voice": "{altitude} overcast {convective}"
            },
            "VV": {
              "text": "VV{altitude}",
              "voice": "indefinite ceiling {altitude}"
            },
            "NSC": {
              "text": "NSC",
              "voice": "no significant clouds"
            },
            "NCD": {
              "text": "NCD",
              "voice": "no clouds detected"
            },
            "CLR": {
              "text": "CLR",
              "voice": "sky clear below one-two thousand"
            },
            "SKC": {
              "text": "SKC",
              "voice": "sky clear"
            }
          },
          "convectiveTypes": {
            "CB": "cumulonimbus",
            "TCU": "towering cumulus"
          },
          "template": {
            "text": "{clouds}",
            "voice": "{clouds}"
          }
        },
        "temperature": {
          "usePlusPrefix": false,
          "speakLeadingZero": false,
          "template": {
            "text": "{temp}",
            "voice": "TEMPERATURE {temp}"
          }
        },
        "dewpoint": {
          "usePlusPrefix": false,
          "speakLeadingZero": false,
          "template": {
            "text": "{dewpoint}",
            "voice": "DEWPOINT {dewpoint}"
          }
        },
        "altimeter": {
          "pronounceDecimal": false,
          "template": {
            "text": "A{altimeter} ({altimeter|text})",
            "voice": "ALTIMETER {altimeter}"
          }
        },
        "transitionLevel": {
          "values": [],
          "template": {
            "text": "TRANSITION LEVEL {trl}",
            "voice": "TRANSITION LEVEL {trl}"
          }
        },
        "closingStatement": {
          "autoIncludeClosingStatement": true,
          "template": {
            "text": "...ADVS YOU HAVE INFO {letter}.",
            "voice": "ADVISE ON INITIAL CONTACT, YOU HAVE INFORMATION {letter|word}"
          }
        }
      },
      "notamsBeforeFreeText": false,
      "airportConditionsBeforeFreeText": false,
      "frequency": 121400000,
      "idsEndpoint": "https://ids-websocket.vzdc.org/api/vatis/flow",
      "useNotamPrefix": false,
      "useDecimalTerminology": false,
      "atisVoice": {
        "useTextToSpeech": true,
        "voice": "US Male"
      },
      "presets": [
        {
          "id": "4e8d4753-2ddd-4986-9746-ab343df41d28",
          "ordinal": 0,
          "name": "East",
          "template": "[FACILITY] ATIS INFO [ATIS_CODE] [TIME]. [WX]. EXPECT ILS/VA RWY 4. MULTIPLE APPROACHES IN EFFECT. LNDG AND DEPG RWY 4. [ARPT_COND] [NOTAMS] TWR CLOSED BETWEEN 1900-0900 LOCAL TIME. C-TAF ON 118.9. @READBACK",
          "externalGenerator": {
            "enabled": false
          }
        },
        {
          "id": "9e6e7c9e-44ad-4c17-8921-b1e5db22fbe8",
          "ordinal": 1,
          "name": "West",
          "template": "[FACILITY] ATIS INFO [ATIS_CODE] [TIME]. [WX]. EXPECT RNAV OR VIS APCH RWY 22. MULTIPLE APPROACHES IN EFFECT. LNDG AND DEPG RWY 22. [ARPT_COND] [NOTAMS] TWR CLOSED BETWEEN 1900-0900 LOCAL TIME. C-TAF ON 118.9. @READBACK",
          "externalGenerator": {
            "enabled": false
          }
        }
      ],
      "contractions": [
        {
          "variableName": "READBACK",
          "text": "READBACK ALL RUNWAY ASSIGNMENTS AND HOLD SHORT INSTRUCTIONS",
          "voice": "READBACK ALL RUNWAY ASSIGNMENTS AND HOLD SHORT INSTRUCTIONS"
        }
      ],
      "airportConditionDefinitions": [],
      "notamDefinitions": []
    },
    {
      "id": "e5a0af78-385d-412c-bcb7-230f25673394",
      "identifier": "KLYH",
      "name": "Lynchburg",
      "atisType": "Combined",
      "codeRange": {
        "low": "A",
        "high": "Z"
      },
      "atisFormat": {
        "observationTime": {
          "template": {
            "text": "{time}Z",
            "voice": "{time} ZULU {special}"
          }
        },
        "surfaceWind": {
          "speakLeadingZero": false,
          "magneticVariation": {
            "enabled": false,
            "magneticDegrees": 0
          },
          "standard": {
            "template": {
              "text": "{wind_dir}{wind_spd}KT",
              "voice": "WIND {wind_dir} AT {wind_spd}"
            }
          },
          "standardGust": {
            "template": {
              "text": "{wind_dir}{wind_spd}G{wind_gust}KT",
              "voice": "WIND {wind_dir} AT {wind_spd} GUSTS {wind_gust}"
            }
          },
          "variable": {
            "template": {
              "text": "VRB{wind_spd}KT",
              "voice": "WIND VARIABLE AT {wind_spd}"
            }
          },
          "variableGust": {
            "template": {
              "text": "VRB{wind_spd}G{wind_gust}KT",
              "voice": "WIND VARIABLE AT {wind_spd} GUSTS {wind_gust}"
            }
          },
          "variableDirection": {
            "template": {
              "text": "{wind_vmin}V{wind_vmax}",
              "voice": "WIND VARIABLE BETWEEN {wind_vmin} AND {wind_vmax}"
            }
          },
          "calm": {
            "calmWindSpeed": 2,
            "template": {
              "text": "{wind}",
              "voice": "WIND CALM"
            }
          }
        },
        "visibility": {
          "north": "to the north",
          "northEast": "to the north-east",
          "east": "to the east",
          "southEast": "to the south-east",
          "south": "to the south",
          "southWest": "to the south-west",
          "west": "to the west",
          "northWest": "to the north-west",
          "unlimitedVisibilityVoice": "visibility 10 kilometers or more",
          "unlimitedVisibilityText": "VIS 10KM",
          "includeVisibilitySuffix": true,
          "metersCutoff": 5000,
          "template": {
            "text": "{visibility}",
            "voice": "VISIBILITY {visibility}"
          }
        },
        "presentWeather": {
          "lightIntensity": "light",
          "moderateIntensity": "",
          "heavyIntensity": "heavy",
          "vicinity": "in vicinity",
          "presentWeatherTypes": {
            "DZ": {
              "text": "DZ",
              "spoken": "drizzle"
            },
            "RA": {
              "text": "RA",
              "spoken": "rain"
            },
            "SN": {
              "text": "SN",
              "spoken": "snow"
            },
            "SG": {
              "text": "SG",
              "spoken": "snow grains"
            },
            "IC": {
              "text": "IC",
              "spoken": "ice crystals"
            },
            "PL": {
              "text": "PL",
              "spoken": "ice pellets"
            },
            "GR": {
              "text": "GR",
              "spoken": "hail"
            },
            "GS": {
              "text": "GS",
              "spoken": "small hail"
            },
            "UP": {
              "text": "UP",
              "spoken": "unknown precipitation"
            },
            "BR": {
              "text": "BR",
              "spoken": "mist"
            },
            "FG": {
              "text": "FG",
              "spoken": "fog"
            },
            "FU": {
              "text": "FU",
              "spoken": "smoke"
            },
            "VA": {
              "text": "VA",
              "spoken": "volcanic ash"
            },
            "DU": {
              "text": "DU",
              "spoken": "widespread dust"
            },
            "SA": {
              "text": "SA",
              "spoken": "sand"
            },
            "HZ": {
              "text": "HZ",
              "spoken": "haze"
            },
            "PY": {
              "text": "PY",
              "spoken": "spray"
            },
            "PO": {
              "text": "PO",
              "spoken": "well developed dust, sand whirls"
            },
            "SQ": {
              "text": "SQ",
              "spoken": "squalls"
            },
            "FC": {
              "text": "FC",
              "spoken": "funnel cloud tornado waterspout"
            },
            "SS": {
              "text": "SS",
              "spoken": "sandstorm"
            },
            "DS": {
              "text": "DS",
              "spoken": "dust storm"
            },
            "PR": {
              "text": "PR",
              "spoken": "partial"
            },
            "BC": {
              "text": "BC",
              "spoken": "patches"
            },
            "MI": {
              "text": "MI",
              "spoken": "shallow"
            },
            "DR": {
              "text": "DR",
              "spoken": "low drifting"
            },
            "BL": {
              "text": "BL",
              "spoken": "blowing"
            },
            "SH": {
              "text": "SH",
              "spoken": "showers"
            },
            "TS": {
              "text": "TS",
              "spoken": "thunderstorm"
            },
            "FZ": {
              "text": "FZ",
              "spoken": "freezing"
            }
          },
          "template": {
            "text": "{weather}",
            "voice": "{weather}"
          }
        },
        "recentWeather": {
          "template": {
            "text": "RECENT WEATHER {weather}",
            "voice": "RECENT WEATHER {weather}"
          }
        },
        "clouds": {
          "identifyCeilingLayer": true,
          "convertToMetric": false,
          "isAltitudeInHundreds": false,
          "undeterminedLayerAltitude": {
            "text": "undetermined",
            "voice": "undetermined"
          },
          "types": {
            "FEW": {
              "text": "FEW{altitude}",
              "voice": "few clouds at {altitude}"
            },
            "SCT": {
              "text": "SCT{altitude}{convective}",
              "voice": "{altitude} scattered {convective}"
            },
            "BKN": {
              "text": "BKN{altitude}{convective}",
              "voice": "{altitude} broken {convective}"
            },
            "OVC": {
              "text": "OVC{altitude}{convective}",
              "voice": "{altitude} overcast {convective}"
            },
            "VV": {
              "text": "VV{altitude}",
              "voice": "indefinite ceiling {altitude}"
            },
            "NSC": {
              "text": "NSC",
              "voice": "no significant clouds"
            },
            "NCD": {
              "text": "NCD",
              "voice": "no clouds detected"
            },
            "CLR": {
              "text": "CLR",
              "voice": "sky clear below one-two thousand"
            },
            "SKC": {
              "text": "SKC",
              "voice": "sky clear"
            }
          },
          "convectiveTypes": {
            "CB": "cumulonimbus",
            "TCU": "towering cumulus"
          },
          "template": {
            "text": "{clouds}",
            "voice": "{clouds}"
          }
        },
        "temperature": {
          "usePlusPrefix": false,
          "speakLeadingZero": false,
          "template": {
            "text": "{temp}",
            "voice": "TEMPERATURE {temp}"
          }
        },
        "dewpoint": {
          "usePlusPrefix": false,
          "speakLeadingZero": false,
          "template": {
            "text": "{dewpoint}",
            "voice": "DEWPOINT {dewpoint}"
          }
        },
        "altimeter": {
          "pronounceDecimal": false,
          "template": {
            "text": "A{altimeter} ({altimeter|text})",
            "voice": "ALTIMETER {altimeter}"
          }
        },
        "transitionLevel": {
          "values": [],
          "template": {
            "text": "TRANSITION LEVEL {trl}",
            "voice": "TRANSITION LEVEL {trl}"
          }
        },
        "closingStatement": {
          "autoIncludeClosingStatement": true,
          "template": {
            "text": "...ADVS YOU HAVE INFO {letter}.",
            "voice": "ADVISE ON INITIAL CONTACT, YOU HAVE INFORMATION {letter|word}"
          }
        }
      },
      "notamsBeforeFreeText": false,
      "airportConditionsBeforeFreeText": false,
      "frequency": 119800000,
      "idsEndpoint": "https://ids-websocket.vzdc.org/api/vatis/flow",
      "useNotamPrefix": false,
      "useDecimalTerminology": false,
      "atisVoice": {
        "useTextToSpeech": true,
        "voice": "US Male"
      },
      "presets": [
        {
          "id": "077d4f9f-3c35-47de-a8cd-f1710832429c",
          "ordinal": 0,
          "name": "West w/17",
          "template": "[FACILITY] ATIS INFO [ATIS_CODE] [TIME]. [WX]. EXPECT RNAV OR VIS APCH RWY 22. MULTIPLE APPROACHES IN EFFECT. LNDG AND DEPG RWY 22. RWY 17 AVAIL UPON REQUEST. [ARPT_COND] [NOTAMS]",
          "externalGenerator": {
            "enabled": false
          }
        },
        {
          "id": "da21f35a-3186-4e45-9828-9d4a651eb20e",
          "ordinal": 1,
          "name": "East w/35",
          "template": "[FACILITY] ATIS INFO [ATIS_CODE] [TIME]. [WX]. EXPECT RNAV OR VIS APCH RWY 4. MULTIPLE APPROACHES IN EFFECT. LNDG AND DEPG RWY 4. RWY 35 AVAIL UPON REQUEST. [ARPT_COND] [NOTAMS]",
          "externalGenerator": {
            "enabled": false
          }
        },
        {
          "id": "fdf9cd56-ddc7-4038-9630-2ee3b14eb41e",
          "ordinal": 2,
          "name": "East",
          "template": "[FACILITY] ATIS INFO [ATIS_CODE] [TIME]. [WX]. EXPECT ILS/VA APCH RWY 4. MULTIPLE APPROACHES IN EFFECT. LNDG AND DEPG RWY 4. [ARPT_COND] [NOTAMS]",
          "externalGenerator": {
            "enabled": false
          }
        },
        {
          "id": "de7712ed-c3b9-4ad0-ba79-02946b0f430c",
          "ordinal": 3,
          "name": "West",
          "template": "[FACILITY] ATIS INFO [ATIS_CODE] [TIME]. [WX]. EXPECT RNAV OR VIS APCH RWY 22. MULTIPLE APPROACHES IN EFFECT. LNDG AND DEPG RWY 22. [ARPT_COND] [NOTAMS]",
          "externalGenerator": {
            "enabled": false
          }
        }
      ],
      "contractions": [],
      "airportConditionDefinitions": [],
      "notamDefinitions": []
    }
  ]
}